{"v":3,"stories":{"가이드--docs":{"id":"가이드--docs","title":"가이드","name":"Docs","importPath":"./src/stories/Configure.mdx","storiesImports":[],"tags":["unattached-mdx","docs"],"kind":"가이드","story":"Docs","parameters":{"__id":"가이드--docs","docsOnly":true,"fileName":"./src/stories/Configure.mdx"}},"foundations-colors--docs":{"id":"foundations-colors--docs","title":"Foundations/Colors","name":"Docs","importPath":"./src/stories/foundations/Colors.mdx","storiesImports":[],"tags":["unattached-mdx","docs"],"kind":"Foundations/Colors","story":"Docs","parameters":{"__id":"foundations-colors--docs","docsOnly":true,"fileName":"./src/stories/foundations/Colors.mdx"}},"foundations-logo--docs":{"id":"foundations-logo--docs","title":"Foundations/Logo","name":"Docs","importPath":"./src/stories/foundations/Logo.mdx","storiesImports":[],"tags":["unattached-mdx","docs"],"kind":"Foundations/Logo","story":"Docs","parameters":{"__id":"foundations-logo--docs","docsOnly":true,"fileName":"./src/stories/foundations/Logo.mdx"}},"foundations-typography--docs":{"id":"foundations-typography--docs","title":"Foundations/Typography","name":"Docs","importPath":"./src/stories/foundations/Typography.mdx","storiesImports":[],"tags":["unattached-mdx","docs"],"kind":"Foundations/Typography","story":"Docs","parameters":{"__id":"foundations-typography--docs","docsOnly":true,"fileName":"./src/stories/foundations/Typography.mdx"}},"components-accordion--docs":{"id":"components-accordion--docs","title":"Components/Accordion","name":"Docs","importPath":"./src/stories/components/accordion/Accordion.stories.tsx","tags":["autodocs","docs"],"storiesImports":[],"kind":"Components/Accordion","story":"Docs","parameters":{"__id":"components-accordion--docs","docsOnly":true,"fileName":"./src/stories/components/accordion/Accordion.stories.tsx"}},"components-accordion--default":{"id":"components-accordion--default","name":"Default","title":"Components/Accordion","importPath":"./src/stories/components/accordion/Accordion.stories.tsx","tags":["autodocs","story"],"kind":"Components/Accordion","story":"Default","parameters":{"__id":"components-accordion--default","docsOnly":false,"fileName":"./src/stories/components/accordion/Accordion.stories.tsx"}},"components-badge--docs":{"id":"components-badge--docs","title":"Components/Badge","name":"Docs","importPath":"./src/stories/components/badge/Badge.stories.tsx","tags":["autodocs","docs"],"storiesImports":[],"kind":"Components/Badge","story":"Docs","parameters":{"__id":"components-badge--docs","docsOnly":true,"fileName":"./src/stories/components/badge/Badge.stories.tsx"}},"components-badge--default":{"id":"components-badge--default","name":"Default","title":"Components/Badge","importPath":"./src/stories/components/badge/Badge.stories.tsx","tags":["autodocs","story"],"kind":"Components/Badge","story":"Default","parameters":{"__id":"components-badge--default","docsOnly":false,"fileName":"./src/stories/components/badge/Badge.stories.tsx"}},"components-badge--all-types":{"id":"components-badge--all-types","name":"All Types","title":"Components/Badge","importPath":"./src/stories/components/badge/Badge.stories.tsx","tags":["autodocs","story"],"kind":"Components/Badge","story":"All Types","parameters":{"__id":"components-badge--all-types","docsOnly":false,"fileName":"./src/stories/components/badge/Badge.stories.tsx"}},"components-button--docs":{"id":"components-button--docs","title":"Components/Button","name":"Docs","importPath":"./src/stories/components/button/Button.stories.tsx","tags":["autodocs","docs"],"storiesImports":[],"kind":"Components/Button","story":"Docs","parameters":{"__id":"components-button--docs","docsOnly":true,"fileName":"./src/stories/components/button/Button.stories.tsx"}},"components-button--default":{"id":"components-button--default","name":"Default","title":"Components/Button","importPath":"./src/stories/components/button/Button.stories.tsx","tags":["autodocs","story"],"kind":"Components/Button","story":"Default","parameters":{"__id":"components-button--default","docsOnly":false,"fileName":"./src/stories/components/button/Button.stories.tsx"}},"components-button--all-types":{"id":"components-button--all-types","name":"All Types","title":"Components/Button","importPath":"./src/stories/components/button/Button.stories.tsx","tags":["autodocs","story"],"kind":"Components/Button","story":"All Types","parameters":{"__id":"components-button--all-types","docsOnly":false,"fileName":"./src/stories/components/button/Button.stories.tsx"}},"components-card--docs":{"id":"components-card--docs","title":"Components/Card","name":"Docs","importPath":"./src/stories/components/card/Card.stories.tsx","tags":["autodocs","docs"],"storiesImports":[],"kind":"Components/Card","story":"Docs","parameters":{"__id":"components-card--docs","docsOnly":true,"fileName":"./src/stories/components/card/Card.stories.tsx"}},"components-card--default":{"id":"components-card--default","name":"Default","title":"Components/Card","importPath":"./src/stories/components/card/Card.stories.tsx","tags":["autodocs","story"],"kind":"Components/Card","story":"Default","parameters":{"__id":"components-card--default","docsOnly":false,"fileName":"./src/stories/components/card/Card.stories.tsx"}},"components-card--all-types":{"id":"components-card--all-types","name":"All Types","title":"Components/Card","importPath":"./src/stories/components/card/Card.stories.tsx","tags":["autodocs","story"],"kind":"Components/Card","story":"All Types","parameters":{"__id":"components-card--all-types","docsOnly":false,"fileName":"./src/stories/components/card/Card.stories.tsx"}},"components-dropdown--docs":{"id":"components-dropdown--docs","title":"Components/Dropdown","name":"Docs","importPath":"./src/stories/components/dropdown/Dropdown.stories.tsx","tags":["autodocs","docs"],"storiesImports":[],"kind":"Components/Dropdown","story":"Docs","parameters":{"__id":"components-dropdown--docs","docsOnly":true,"fileName":"./src/stories/components/dropdown/Dropdown.stories.tsx"}},"components-dropdown--default":{"id":"components-dropdown--default","name":"Default","title":"Components/Dropdown","importPath":"./src/stories/components/dropdown/Dropdown.stories.tsx","tags":["autodocs","story"],"kind":"Components/Dropdown","story":"Default","parameters":{"__id":"components-dropdown--default","docsOnly":false,"fileName":"./src/stories/components/dropdown/Dropdown.stories.tsx"}},"components-dropdown--all-types":{"id":"components-dropdown--all-types","name":"All Types","title":"Components/Dropdown","importPath":"./src/stories/components/dropdown/Dropdown.stories.tsx","tags":["autodocs","story"],"kind":"Components/Dropdown","story":"All Types","parameters":{"__id":"components-dropdown--all-types","docsOnly":false,"fileName":"./src/stories/components/dropdown/Dropdown.stories.tsx"}},"components-icon--docs":{"id":"components-icon--docs","title":"Components/Icon","name":"Docs","importPath":"./src/stories/components/Icon/Icon.stories.tsx","tags":["autodocs","docs"],"storiesImports":[],"kind":"Components/Icon","story":"Docs","parameters":{"__id":"components-icon--docs","docsOnly":true,"fileName":"./src/stories/components/Icon/Icon.stories.tsx"}},"components-icon--default":{"id":"components-icon--default","name":"Default","title":"Components/Icon","importPath":"./src/stories/components/Icon/Icon.stories.tsx","tags":["autodocs","story"],"kind":"Components/Icon","story":"Default","parameters":{"__id":"components-icon--default","docsOnly":false,"fileName":"./src/stories/components/Icon/Icon.stories.tsx"}},"components-icon--all-types":{"id":"components-icon--all-types","name":"All Types","title":"Components/Icon","importPath":"./src/stories/components/Icon/Icon.stories.tsx","tags":["autodocs","story"],"kind":"Components/Icon","story":"All Types","parameters":{"__id":"components-icon--all-types","docsOnly":false,"fileName":"./src/stories/components/Icon/Icon.stories.tsx"}},"components-loading--docs":{"id":"components-loading--docs","title":"Components/Loading","name":"Docs","importPath":"./src/stories/components/loading/Loading.stories.tsx","tags":["autodocs","docs"],"storiesImports":[],"kind":"Components/Loading","story":"Docs","parameters":{"__id":"components-loading--docs","docsOnly":true,"fileName":"./src/stories/components/loading/Loading.stories.tsx"}},"components-loading--default":{"id":"components-loading--default","name":"Default","title":"Components/Loading","importPath":"./src/stories/components/loading/Loading.stories.tsx","tags":["autodocs","story"],"kind":"Components/Loading","story":"Default","parameters":{"__id":"components-loading--default","docsOnly":false,"fileName":"./src/stories/components/loading/Loading.stories.tsx"}},"components-modal--docs":{"id":"components-modal--docs","title":"Components/Modal","name":"Docs","importPath":"./src/stories/components/modal/Modal.stories.tsx","tags":["autodocs","docs"],"storiesImports":[],"kind":"Components/Modal","story":"Docs","parameters":{"__id":"components-modal--docs","docsOnly":true,"fileName":"./src/stories/components/modal/Modal.stories.tsx"}},"components-modal--default":{"id":"components-modal--default","name":"Default","title":"Components/Modal","importPath":"./src/stories/components/modal/Modal.stories.tsx","tags":["autodocs","story"],"kind":"Components/Modal","story":"Default","parameters":{"__id":"components-modal--default","docsOnly":false,"fileName":"./src/stories/components/modal/Modal.stories.tsx"}},"components-modal--all-types":{"id":"components-modal--all-types","name":"All Types","title":"Components/Modal","importPath":"./src/stories/components/modal/Modal.stories.tsx","tags":["autodocs","story"],"kind":"Components/Modal","story":"All Types","parameters":{"__id":"components-modal--all-types","docsOnly":false,"fileName":"./src/stories/components/modal/Modal.stories.tsx"}},"components-pagination--docs":{"id":"components-pagination--docs","title":"Components/Pagination","name":"Docs","importPath":"./src/stories/components/pagination/Pagination.stories.tsx","tags":["autodocs","docs"],"storiesImports":[],"kind":"Components/Pagination","story":"Docs","parameters":{"__id":"components-pagination--docs","docsOnly":true,"fileName":"./src/stories/components/pagination/Pagination.stories.tsx"}},"components-pagination--default":{"id":"components-pagination--default","name":"Default","title":"Components/Pagination","importPath":"./src/stories/components/pagination/Pagination.stories.tsx","tags":["autodocs","story"],"kind":"Components/Pagination","story":"Default","parameters":{"__id":"components-pagination--default","docsOnly":false,"fileName":"./src/stories/components/pagination/Pagination.stories.tsx"}},"components-pagination--all-types":{"id":"components-pagination--all-types","name":"All Types","title":"Components/Pagination","importPath":"./src/stories/components/pagination/Pagination.stories.tsx","tags":["autodocs","story"],"kind":"Components/Pagination","story":"All Types","parameters":{"__id":"components-pagination--all-types","docsOnly":false,"fileName":"./src/stories/components/pagination/Pagination.stories.tsx"}},"components-progressbar--docs":{"id":"components-progressbar--docs","title":"Components/ProgressBar","name":"Docs","importPath":"./src/stories/components/progressbar/ProgressBar.stories.tsx","tags":["autodocs","docs"],"storiesImports":[],"kind":"Components/ProgressBar","story":"Docs","parameters":{"__id":"components-progressbar--docs","docsOnly":true,"fileName":"./src/stories/components/progressbar/ProgressBar.stories.tsx"}},"components-progressbar--default":{"id":"components-progressbar--default","name":"Default","title":"Components/ProgressBar","importPath":"./src/stories/components/progressbar/ProgressBar.stories.tsx","tags":["autodocs","story"],"kind":"Components/ProgressBar","story":"Default","parameters":{"__id":"components-progressbar--default","docsOnly":false,"fileName":"./src/stories/components/progressbar/ProgressBar.stories.tsx"}},"components-progressbar--all-types":{"id":"components-progressbar--all-types","name":"All Types","title":"Components/ProgressBar","importPath":"./src/stories/components/progressbar/ProgressBar.stories.tsx","tags":["autodocs","story"],"kind":"Components/ProgressBar","story":"All Types","parameters":{"__id":"components-progressbar--all-types","docsOnly":false,"fileName":"./src/stories/components/progressbar/ProgressBar.stories.tsx"}},"components-tooltip--docs":{"id":"components-tooltip--docs","title":"Components/Tooltip","name":"Docs","importPath":"./src/stories/components/tooltip/Tooltip.stories.tsx","tags":["autodocs","docs"],"storiesImports":[],"kind":"Components/Tooltip","story":"Docs","parameters":{"__id":"components-tooltip--docs","docsOnly":true,"fileName":"./src/stories/components/tooltip/Tooltip.stories.tsx"}},"components-tooltip--default":{"id":"components-tooltip--default","name":"Default","title":"Components/Tooltip","importPath":"./src/stories/components/tooltip/Tooltip.stories.tsx","tags":["autodocs","story"],"kind":"Components/Tooltip","story":"Default","parameters":{"__id":"components-tooltip--default","docsOnly":false,"fileName":"./src/stories/components/tooltip/Tooltip.stories.tsx"}},"components-tooltip--all-types":{"id":"components-tooltip--all-types","name":"All Types","title":"Components/Tooltip","importPath":"./src/stories/components/tooltip/Tooltip.stories.tsx","tags":["autodocs","story"],"kind":"Components/Tooltip","story":"All Types","parameters":{"__id":"components-tooltip--all-types","docsOnly":false,"fileName":"./src/stories/components/tooltip/Tooltip.stories.tsx"}},"forms-checkbox--docs":{"id":"forms-checkbox--docs","title":"Forms/Checkbox","name":"Docs","importPath":"./src/stories/forms/checkbox/Checkbox.stories.tsx","tags":["autodocs","docs"],"storiesImports":[],"kind":"Forms/Checkbox","story":"Docs","parameters":{"__id":"forms-checkbox--docs","docsOnly":true,"fileName":"./src/stories/forms/checkbox/Checkbox.stories.tsx"}},"forms-checkbox--default":{"id":"forms-checkbox--default","name":"Default","title":"Forms/Checkbox","importPath":"./src/stories/forms/checkbox/Checkbox.stories.tsx","tags":["autodocs","story"],"kind":"Forms/Checkbox","story":"Default","parameters":{"__id":"forms-checkbox--default","docsOnly":false,"fileName":"./src/stories/forms/checkbox/Checkbox.stories.tsx"}},"forms-checkbox--all-types":{"id":"forms-checkbox--all-types","name":"All Types","title":"Forms/Checkbox","importPath":"./src/stories/forms/checkbox/Checkbox.stories.tsx","tags":["autodocs","story"],"kind":"Forms/Checkbox","story":"All Types","parameters":{"__id":"forms-checkbox--all-types","docsOnly":false,"fileName":"./src/stories/forms/checkbox/Checkbox.stories.tsx"}},"forms-input--docs":{"id":"forms-input--docs","title":"Forms/Input","name":"Docs","importPath":"./src/stories/forms/input/Input.stories.tsx","tags":["autodocs","docs"],"storiesImports":[],"kind":"Forms/Input","story":"Docs","parameters":{"__id":"forms-input--docs","docsOnly":true,"fileName":"./src/stories/forms/input/Input.stories.tsx"}},"forms-input--default":{"id":"forms-input--default","name":"Default","title":"Forms/Input","importPath":"./src/stories/forms/input/Input.stories.tsx","tags":["autodocs","story"],"kind":"Forms/Input","story":"Default","parameters":{"__id":"forms-input--default","docsOnly":false,"fileName":"./src/stories/forms/input/Input.stories.tsx"}},"forms-input--all-types":{"id":"forms-input--all-types","name":"All Types","title":"Forms/Input","importPath":"./src/stories/forms/input/Input.stories.tsx","tags":["autodocs","story"],"kind":"Forms/Input","story":"All Types","parameters":{"__id":"forms-input--all-types","docsOnly":false,"fileName":"./src/stories/forms/input/Input.stories.tsx"}},"forms-radio--docs":{"id":"forms-radio--docs","title":"Forms/Radio","name":"Docs","importPath":"./src/stories/forms/radio/Radio.stories.tsx","tags":["autodocs","docs"],"storiesImports":[],"kind":"Forms/Radio","story":"Docs","parameters":{"__id":"forms-radio--docs","docsOnly":true,"fileName":"./src/stories/forms/radio/Radio.stories.tsx"}},"forms-radio--default":{"id":"forms-radio--default","name":"Default","title":"Forms/Radio","importPath":"./src/stories/forms/radio/Radio.stories.tsx","tags":["autodocs","story"],"kind":"Forms/Radio","story":"Default","parameters":{"__id":"forms-radio--default","docsOnly":false,"fileName":"./src/stories/forms/radio/Radio.stories.tsx"}},"forms-radio--all-types":{"id":"forms-radio--all-types","name":"All Types","title":"Forms/Radio","importPath":"./src/stories/forms/radio/Radio.stories.tsx","tags":["autodocs","story"],"kind":"Forms/Radio","story":"All Types","parameters":{"__id":"forms-radio--all-types","docsOnly":false,"fileName":"./src/stories/forms/radio/Radio.stories.tsx"}},"forms-select--docs":{"id":"forms-select--docs","title":"Forms/Select","name":"Docs","importPath":"./src/stories/forms/select/Select.stories.tsx","tags":["autodocs","docs"],"storiesImports":[],"kind":"Forms/Select","story":"Docs","parameters":{"__id":"forms-select--docs","docsOnly":true,"fileName":"./src/stories/forms/select/Select.stories.tsx"}},"forms-select--primary":{"id":"forms-select--primary","name":"Default","title":"Forms/Select","importPath":"./src/stories/forms/select/Select.stories.tsx","tags":["autodocs","story"],"kind":"Forms/Select","story":"Default","parameters":{"__id":"forms-select--primary","docsOnly":false,"fileName":"./src/stories/forms/select/Select.stories.tsx"}},"forms-select--all-types":{"id":"forms-select--all-types","name":"All Types","title":"Forms/Select","importPath":"./src/stories/forms/select/Select.stories.tsx","tags":["autodocs","story"],"kind":"Forms/Select","story":"All Types","parameters":{"__id":"forms-select--all-types","docsOnly":false,"fileName":"./src/stories/forms/select/Select.stories.tsx"}},"forms-switch--docs":{"id":"forms-switch--docs","title":"Forms/Switch","name":"Docs","importPath":"./src/stories/forms/switch/Switch.stories.tsx","tags":["autodocs","docs"],"storiesImports":[],"kind":"Forms/Switch","story":"Docs","parameters":{"__id":"forms-switch--docs","docsOnly":true,"fileName":"./src/stories/forms/switch/Switch.stories.tsx"}},"forms-switch--default":{"id":"forms-switch--default","name":"Default","title":"Forms/Switch","importPath":"./src/stories/forms/switch/Switch.stories.tsx","tags":["autodocs","story"],"kind":"Forms/Switch","story":"Default","parameters":{"__id":"forms-switch--default","docsOnly":false,"fileName":"./src/stories/forms/switch/Switch.stories.tsx"}},"forms-switch--all-types":{"id":"forms-switch--all-types","name":"All Types","title":"Forms/Switch","importPath":"./src/stories/forms/switch/Switch.stories.tsx","tags":["autodocs","story"],"kind":"Forms/Switch","story":"All Types","parameters":{"__id":"forms-switch--all-types","docsOnly":false,"fileName":"./src/stories/forms/switch/Switch.stories.tsx"}},"forms-textarea--docs":{"id":"forms-textarea--docs","title":"Forms/Textarea","name":"Docs","importPath":"./src/stories/forms/textarea/Textarea.stories.tsx","tags":["autodocs","docs"],"storiesImports":[],"kind":"Forms/Textarea","story":"Docs","parameters":{"__id":"forms-textarea--docs","docsOnly":true,"fileName":"./src/stories/forms/textarea/Textarea.stories.tsx"}},"forms-textarea--default":{"id":"forms-textarea--default","name":"Default","title":"Forms/Textarea","importPath":"./src/stories/forms/textarea/Textarea.stories.tsx","tags":["autodocs","story"],"kind":"Forms/Textarea","story":"Default","parameters":{"__id":"forms-textarea--default","docsOnly":false,"fileName":"./src/stories/forms/textarea/Textarea.stories.tsx"}},"forms-textarea--all-types":{"id":"forms-textarea--all-types","name":"All Types","title":"Forms/Textarea","importPath":"./src/stories/forms/textarea/Textarea.stories.tsx","tags":["autodocs","story"],"kind":"Forms/Textarea","story":"All Types","parameters":{"__id":"forms-textarea--all-types","docsOnly":false,"fileName":"./src/stories/forms/textarea/Textarea.stories.tsx"}},"layout-footer--docs":{"id":"layout-footer--docs","title":"Layout/Footer","name":"Docs","importPath":"./src/stories/layout/footer/Footer.stories.tsx","tags":["autodocs","docs"],"storiesImports":[],"kind":"Layout/Footer","story":"Docs","parameters":{"__id":"layout-footer--docs","docsOnly":true,"fileName":"./src/stories/layout/footer/Footer.stories.tsx"}},"layout-footer--default":{"id":"layout-footer--default","name":"Default","title":"Layout/Footer","importPath":"./src/stories/layout/footer/Footer.stories.tsx","tags":["autodocs","story"],"kind":"Layout/Footer","story":"Default","parameters":{"__id":"layout-footer--default","docsOnly":false,"fileName":"./src/stories/layout/footer/Footer.stories.tsx"}},"layout-header--docs":{"id":"layout-header--docs","title":"Layout/Header","name":"Docs","importPath":"./src/stories/layout/header/Header.stories.tsx","tags":["autodocs","docs"],"storiesImports":[],"kind":"Layout/Header","story":"Docs","parameters":{"__id":"layout-header--docs","docsOnly":true,"fileName":"./src/stories/layout/header/Header.stories.tsx"}},"layout-header--default":{"id":"layout-header--default","name":"Default","title":"Layout/Header","importPath":"./src/stories/layout/header/Header.stories.tsx","tags":["autodocs","story"],"kind":"Layout/Header","story":"Default","parameters":{"__id":"layout-header--default","docsOnly":false,"fileName":"./src/stories/layout/header/Header.stories.tsx"}},"layout-sidebar--docs":{"id":"layout-sidebar--docs","title":"Layout/Sidebar","name":"Docs","importPath":"./src/stories/layout/sidebar/Sidebar.stories.tsx","tags":["autodocs","docs"],"storiesImports":[],"kind":"Layout/Sidebar","story":"Docs","parameters":{"__id":"layout-sidebar--docs","docsOnly":true,"fileName":"./src/stories/layout/sidebar/Sidebar.stories.tsx"}},"layout-sidebar--default":{"id":"layout-sidebar--default","name":"Default","title":"Layout/Sidebar","importPath":"./src/stories/layout/sidebar/Sidebar.stories.tsx","tags":["autodocs","story"],"kind":"Layout/Sidebar","story":"Default","parameters":{"__id":"layout-sidebar--default","docsOnly":false,"fileName":"./src/stories/layout/sidebar/Sidebar.stories.tsx"}},"example-button--docs":{"id":"example-button--docs","title":"Example/Button","name":"Docs","importPath":"./src/stories/example/button/Button.stories.ts","tags":["autodocs","docs"],"storiesImports":[],"kind":"Example/Button","story":"Docs","parameters":{"__id":"example-button--docs","docsOnly":true,"fileName":"./src/stories/example/button/Button.stories.ts"}},"example-button--large":{"id":"example-button--large","name":"Large","title":"Example/Button","importPath":"./src/stories/example/button/Button.stories.ts","tags":["autodocs","story"],"kind":"Example/Button","story":"Large","parameters":{"__id":"example-button--large","docsOnly":false,"fileName":"./src/stories/example/button/Button.stories.ts"}},"example-button--primary":{"id":"example-button--primary","name":"Primary","title":"Example/Button","importPath":"./src/stories/example/button/Button.stories.ts","tags":["autodocs","story"],"kind":"Example/Button","story":"Primary","parameters":{"__id":"example-button--primary","docsOnly":false,"fileName":"./src/stories/example/button/Button.stories.ts"}},"example-button--secondary":{"id":"example-button--secondary","name":"Secondary","title":"Example/Button","importPath":"./src/stories/example/button/Button.stories.ts","tags":["autodocs","story"],"kind":"Example/Button","story":"Secondary","parameters":{"__id":"example-button--secondary","docsOnly":false,"fileName":"./src/stories/example/button/Button.stories.ts"}},"example-button--small":{"id":"example-button--small","name":"Small","title":"Example/Button","importPath":"./src/stories/example/button/Button.stories.ts","tags":["autodocs","story"],"kind":"Example/Button","story":"Small","parameters":{"__id":"example-button--small","docsOnly":false,"fileName":"./src/stories/example/button/Button.stories.ts"}},"example-header--docs":{"id":"example-header--docs","title":"Example/Header","name":"Docs","importPath":"./src/stories/example/header/Header.stories.ts","tags":["autodocs","docs"],"storiesImports":[],"kind":"Example/Header","story":"Docs","parameters":{"__id":"example-header--docs","docsOnly":true,"fileName":"./src/stories/example/header/Header.stories.ts"}},"example-header--logged-in":{"id":"example-header--logged-in","name":"Logged In","title":"Example/Header","importPath":"./src/stories/example/header/Header.stories.ts","tags":["autodocs","story"],"kind":"Example/Header","story":"Logged In","parameters":{"__id":"example-header--logged-in","docsOnly":false,"fileName":"./src/stories/example/header/Header.stories.ts"}},"example-header--logged-out":{"id":"example-header--logged-out","name":"Logged Out","title":"Example/Header","importPath":"./src/stories/example/header/Header.stories.ts","tags":["autodocs","story"],"kind":"Example/Header","story":"Logged Out","parameters":{"__id":"example-header--logged-out","docsOnly":false,"fileName":"./src/stories/example/header/Header.stories.ts"}},"example-page--logged-in":{"id":"example-page--logged-in","name":"Logged In","title":"Example/Page","importPath":"./src/stories/example/page/Page.stories.ts","tags":["play-fn","story"],"kind":"Example/Page","story":"Logged In","parameters":{"__id":"example-page--logged-in","docsOnly":false,"fileName":"./src/stories/example/page/Page.stories.ts"}},"example-page--logged-out":{"id":"example-page--logged-out","name":"Logged Out","title":"Example/Page","importPath":"./src/stories/example/page/Page.stories.ts","tags":["story"],"kind":"Example/Page","story":"Logged Out","parameters":{"__id":"example-page--logged-out","docsOnly":false,"fileName":"./src/stories/example/page/Page.stories.ts"}}}}
